setup.py
th_distributions/Binomialdistribution.py
th_distributions/Gaussiandistribution.py
th_distributions/Generaldistribution.py
th_distributions/__init__.py
th_distributions.egg-info/PKG-INFO
th_distributions.egg-info/SOURCES.txt
th_distributions.egg-info/dependency_links.txt
th_distributions.egg-info/not-zip-safe
th_distributions.egg-info/top_level.txt