Metadata-Version: 1.0
Name: th-distributions
Version: 0.1
Summary: Gaussian and Binomial distributions
Home-page: UNKNOWN
Author: Travis Helm
Author-email: travhao@gmail.com
License: UNKNOWN
Platform: UNKNOWN
